LICENSE
MANIFEST.in
README.md
setup.cfg
setup.py
r2pipe/__init__.py
r2pipe/native.py
r2pipe/open_async.py
r2pipe/open_base.py
r2pipe/open_sync.py
r2pipe.egg-info/PKG-INFO
r2pipe.egg-info/SOURCES.txt
r2pipe.egg-info/dependency_links.txt
r2pipe.egg-info/top_level.txt
test/test_async_enhanced.py
test/test_error_handling.py
test/test_integration.py
test/test_native_enhanced.py
test/test_network.py
test/test_sync_enhanced.py
test/test_unit.py