Metadata-Version: 2.1
Name: r2pipe
Version: 1.9.6
Summary: Pipe interface for radare2
Home-page: https://rada.re
Author: pancake
Author-email: pancake@nopcode.org
License: MIT
License-File: LICENSE
